<xml><transactions><transaction date="1548285341" type="wf_export_document_attributes" vaultname="Testbox"><document aliasset="" id="GB1-5715-00-00" idattribute="Number" idcfgname="Default" pdmweid="3013"><configuration name="Default" quantity="1"><attribute name="Number" value="GB1-5715-00-00"/><attribute name="Part Family" value="0"/><attribute name="Part Type" value="P"/><attribute name="Buy / Sell Unit" value="ea"/><attribute name="Revision" value="A03"/><attribute name="Conversion Ratio" value="1"/><attribute name="Assigned To" value="TomA"/><attribute name="Description" value="Main Spar LH"/><attribute name="Factory Unit" value="ea"/><attribute name="PDFLocation" value="D:\EPDM_Output\DW-GB1-5715-00-00.PDF"/><attribute name="ECO Details" value="Main Spar LH"/><attribute name="ECO Reason" value="New"/><attribute name="Code" value="1"/><attribute name="State" value="Released"/><attribute name="Reference Count" value="1.0"/><references><document aliasset="" id="C200" idattribute="Number" idcfgname="Default" pdmweid="1016"><configuration name="Default" quantity="28"><attribute name="Number" value="C200"/><attribute name="Part Family" value="Fabrics"/><attribute name="Part Type" value="R"/><attribute name="Buy / Sell Unit" value="m"/><attribute name="Revision" value="A03"/><attribute name="Conversion Ratio" value="1"/><attribute name="Assigned To" value="TomA"/><attribute name="Description" value="EC Cramer CCC452"/><attribute name="Factory Unit" value="m"/><attribute name="PDFLocation" value="D:\EPDM_Output\DW-C200.PDF"/><attribute name="ECO Details" value="EC Cramer CCC452"/><attribute name="ECO Reason" value="New"/><attribute name="Code" value="1"/><attribute name="State" value="Released"/><attribute name="Reference Count" value="28.0"/></configuration></document><document aliasset="" id="EPL20" idattribute="Number" idcfgname="Default" pdmweid="1326"><configuration name="Default" quantity="4200"><attribute name="Number" value="EPL20"/><attribute name="Part Family" value="Resins"/><attribute name="Part Type" value="R"/><attribute name="Buy / Sell Unit" value="kg"/><attribute name="Revision" value="B01"/><attribute name="Conversion Ratio" value="1000"/><attribute name="Assigned To" value="AlisonS"/><attribute name="Description" value="Resin Momentive EPL20"/><attribute name="Factory Unit" value="gm"/><attribute name="PDFLocation" value="D:\EPDM_Output\DW-EPL20.PDF"/><attribute name="ECO Details" value="Resin type change"/><attribute name="ECO Reason" value="New"/><attribute name="Code" value="1"/><attribute name="State" value="Released"/><attribute name="Reference Count" value="4200.0"/></configuration></document><document aliasset="" id="EK960" idattribute="Number" idcfgname="Default" pdmweid="1327"><configuration name="Default" quantity="1400"><attribute name="Number" value="EK960"/><attribute name="Part Family" value="Resins"/><attribute name="Part Type" value="R"/><attribute name="Buy / Sell Unit" value="kg"/><attribute name="Revision" value="B01"/><attribute name="Conversion Ratio" value="1000"/><attribute name="Assigned To" value="AlisonS"/><attribute name="Description" value="Hardener Momentive EK960"/><attribute name="Factory Unit" value="gm"/><attribute name="PDFLocation" value="D:\EPDM_Output\DW-EK960.PDF"/><attribute name="ECO Details" value="Hardener type change"/><attribute name="ECO Reason" value="New"/><attribute name="Code" value="1"/><attribute name="State" value="Released"/><attribute name="Reference Count" value="1400.0"/></configuration></document><document aliasset="" id="505814GM" idattribute="Number" idcfgname="Default" pdmweid="1534"><configuration name="Default" quantity="2"><attribute name="Number" value="505814GM"/><attribute name="Part Family" value="Std-Part"/><attribute name="Part Type" value="R"/><attribute name="Buy / Sell Unit" value="ea"/><attribute name="Revision" value="A02"/><attribute name="Conversion Ratio" value="1"/><attribute name="Assigned To" value="AlisonS"/><attribute name="Description" value="Bush, 505814GM"/><attribute name="Factory Unit" value="ea"/><attribute name="PDFLocation" value="D:\EPDM_Output\DW-505814GM.PDF"/><attribute name="ECO Details" value="Bush 505814GM second release"/><attribute name="ECO Reason" value="New"/><attribute name="Code" value="1"/><attribute name="State" value="Work In Progress"/><attribute name="Reference Count" value="2.0"/></configuration></document><document aliasset="" id="Cotton-Flox" idattribute="Number" idcfgname="Default" pdmweid="1640"><configuration name="Default" quantity="10"><attribute name="Number" value="Cotton-Flox"/><attribute name="Part Family" value="Prod-Con"/><attribute name="Part Type" value="R"/><attribute name="Buy / Sell Unit" value="ea"/><attribute name="Revision" value="A01"/><attribute name="Conversion Ratio" value="1000"/><attribute name="Assigned To" value="AlisonS"/><attribute name="Description" value="Cotton Flox"/><attribute name="Factory Unit" value="gm"/><attribute name="PDFLocation" value="D:\EPDM_Output\DW-Cotton-Flox.PDF"/><attribute name="ECO Details" value="New cotton flox"/><attribute name="ECO Reason" value="New"/><attribute name="Code" value="1"/><attribute name="State" value="Released"/><attribute name="Reference Count" value="10.0"/></configuration></document><document aliasset="" id="GT163" idattribute="Number" idcfgname="Default" pdmweid="1878"><configuration name="Default" quantity="1"><attribute name="Number" value="GT163"/><attribute name="Part Family" value="Fabrics"/><attribute name="Part Type" value="R"/><attribute name="Buy / Sell Unit" value="m"/><attribute name="Revision" value="A02"/><attribute name="Conversion Ratio" value="1"/><attribute name="Assigned To" value="AlisonS"/><attribute name="Description" value="Interglas 163g/sqm, Aero, FK 144, twill"/><attribute name="Factory Unit" value="sqm"/><attribute name="PDFLocation" value="D:\EPDM_Output\DW-GT163.PDF"/><attribute name="ECO Details" value="GT163 decription shortened"/><attribute name="ECO Reason" value="New"/><attribute name="Code" value="1"/><attribute name="State" value="Released"/><attribute name="Reference Count" value="1.0"/></configuration></document><document aliasset="" id="GB1-5715-00-02" idattribute="Number" idcfgname="Default" pdmweid="3498"><configuration name="Default" quantity="1"><attribute name="Number" value="GB1-5715-00-02"/><attribute name="Part Family" value="0"/><attribute name="Part Type" value="P"/><attribute name="Buy / Sell Unit" value="ea"/><attribute name="Revision" value="A03"/><attribute name="Conversion Ratio" value="1"/><attribute name="Assigned To" value=""/><attribute name="Description" value="Main Spar LH Lower Cap"/><attribute name="Factory Unit" value="ea"/><attribute name="PDFLocation" value="D:\EPDM_Output\DW-GB1-5715-00-02.PDF"/><attribute name="ECO Details" value="Main Spar LH Lower Cap"/><attribute name="ECO Reason" value="New"/><attribute name="Code" value="1"/><attribute name="State" value="Released"/><attribute name="Reference Count" value="1.0"/><references><document aliasset="" id="GB1-5715-92-00" idattribute="Number" idcfgname="Default" pdmweid="3483"><configuration name="Default" quantity="1"><attribute name="Number" value="GB1-5715-92-00"/><attribute name="Part Family" value="0"/><attribute name="Part Type" value="P"/><attribute name="Buy / Sell Unit" value="ea"/><attribute name="Revision" value="A02"/><attribute name="Conversion Ratio" value="8"/><attribute name="Assigned To" value="TomA"/><attribute name="Description" value="Main Spar Lower Cap Plate"/><attribute name="Factory Unit" value="ea"/><attribute name="PDFLocation" value="D:\EPDM_Output\DW-GB1-5715-92-00.PDF"/><attribute name="ECO Details" value="Main Spar Lower Cap Plate"/><attribute name="ECO Reason" value="New"/><attribute name="Code" value="1"/><attribute name="State" value="Released"/><attribute name="Reference Count" value="1.0"/><references><document aliasset="" id="CU300" idattribute="Number" idcfgname="Default" pdmweid="1019"><configuration name="Default" quantity="87"><attribute name="Number" value="CU300"/><attribute name="Part Family" value="Fabrics"/><attribute name="Part Type" value="R"/><attribute name="Buy / Sell Unit" value="m"/><attribute name="Revision" value="A03"/><attribute name="Conversion Ratio" value="1"/><attribute name="Assigned To" value=""/><attribute name="Description" value="EC Cramer AU030"/><attribute name="Factory Unit" value="m"/><attribute name="PDFLocation" value="D:\EPDM_Output\DW-CU300.PDF"/><attribute name="ECO Details" value="EC Cramer AU030"/><attribute name="ECO Reason" value="New"/><attribute name="Code" value="1"/><attribute name="State" value="Released"/><attribute name="Reference Count" value="87.0"/></configuration></document><document aliasset="" id="EPL20" idattribute="Number" idcfgname="Default" pdmweid="1326"><configuration name="Default" quantity="23100"><attribute name="Number" value="EPL20"/><attribute name="Part Family" value="Resins"/><attribute name="Part Type" value="R"/><attribute name="Buy / Sell Unit" value="kg"/><attribute name="Revision" value="B01"/><attribute name="Conversion Ratio" value="1000"/><attribute name="Assigned To" value="AlisonS"/><attribute name="Description" value="Resin Momentive EPL20"/><attribute name="Factory Unit" value="gm"/><attribute name="PDFLocation" value="D:\EPDM_Output\DW-EPL20.PDF"/><attribute name="ECO Details" value="Resin type change"/><attribute name="ECO Reason" value="New"/><attribute name="Code" value="1"/><attribute name="State" value="Released"/><attribute name="Reference Count" value="23100.0"/></configuration></document><document aliasset="" id="EK960" idattribute="Number" idcfgname="Default" pdmweid="1327"><configuration name="Default" quantity="7700"><attribute name="Number" value="EK960"/><attribute name="Part Family" value="Resins"/><attribute name="Part Type" value="R"/><attribute name="Buy / Sell Unit" value="kg"/><attribute name="Revision" value="B01"/><attribute name="Conversion Ratio" value="1000"/><attribute name="Assigned To" value="AlisonS"/><attribute name="Description" value="Hardener Momentive EK960"/><attribute name="Factory Unit" value="gm"/><attribute name="PDFLocation" value="D:\EPDM_Output\DW-EK960.PDF"/><attribute name="ECO Details" value="Hardener type change"/><attribute name="ECO Reason" value="New"/><attribute name="Code" value="1"/><attribute name="State" value="Released"/><attribute name="Reference Count" value="7700.0"/></configuration></document></references></configuration></document></references></configuration></document><document aliasset="" id="GB1-5715-00-01" idattribute="Number" idcfgname="Default" pdmweid="3579"><configuration name="Default" quantity="1"><attribute name="Number" value="GB1-5715-00-01"/><attribute name="Part Family" value="0"/><attribute name="Part Type" value="P"/><attribute name="Buy / Sell Unit" value="ea"/><attribute name="Revision" value="A02"/><attribute name="Conversion Ratio" value="1"/><attribute name="Assigned To" value=""/><attribute name="Description" value="Main Spar LH Upper Cap"/><attribute name="Factory Unit" value="ea"/><attribute name="PDFLocation" value="D:\EPDM_Output\DW-GB1-5715-00-01.PDF"/><attribute name="ECO Details" value="Main Spar LH Upper Cap"/><attribute name="ECO Reason" value="New"/><attribute name="Code" value="1"/><attribute name="State" value="Released"/><attribute name="Reference Count" value="1.0"/><references><document aliasset="" id="GB1-5715-91-00" idattribute="Number" idcfgname="Default" pdmweid="3532"><configuration name="Default" quantity="1"><attribute name="Number" value="GB1-5715-91-00"/><attribute name="Part Family" value="0"/><attribute name="Part Type" value="P"/><attribute name="Buy / Sell Unit" value="ea"/><attribute name="Revision" value="A02"/><attribute name="Conversion Ratio" value="8"/><attribute name="Assigned To" value="TomA"/><attribute name="Description" value="Main Spar Upper Cap Plate"/><attribute name="Factory Unit" value="ea"/><attribute name="PDFLocation" value="D:\EPDM_Output\DW-GB1-5715-91-00.PDF"/><attribute name="ECO Details" value="Main Spar Upper Cap Plate"/><attribute name="ECO Reason" value="New"/><attribute name="Code" value="1"/><attribute name="State" value="Released"/><attribute name="Reference Count" value="1.0"/><references><document aliasset="" id="CU300" idattribute="Number" idcfgname="Default" pdmweid="1019"><configuration name="Default" quantity="87"><attribute name="Number" value="CU300"/><attribute name="Part Family" value="Fabrics"/><attribute name="Part Type" value="R"/><attribute name="Buy / Sell Unit" value="m"/><attribute name="Revision" value="A03"/><attribute name="Conversion Ratio" value="1"/><attribute name="Assigned To" value=""/><attribute name="Description" value="EC Cramer AU030"/><attribute name="Factory Unit" value="m"/><attribute name="PDFLocation" value="D:\EPDM_Output\DW-CU300.PDF"/><attribute name="ECO Details" value="EC Cramer AU030"/><attribute name="ECO Reason" value="New"/><attribute name="Code" value="1"/><attribute name="State" value="Released"/><attribute name="Reference Count" value="87.0"/></configuration></document><document aliasset="" id="EPL20" idattribute="Number" idcfgname="Default" pdmweid="1326"><configuration name="Default" quantity="23100"><attribute name="Number" value="EPL20"/><attribute name="Part Family" value="Resins"/><attribute name="Part Type" value="R"/><attribute name="Buy / Sell Unit" value="kg"/><attribute name="Revision" value="B01"/><attribute name="Conversion Ratio" value="1000"/><attribute name="Assigned To" value="AlisonS"/><attribute name="Description" value="Resin Momentive EPL20"/><attribute name="Factory Unit" value="gm"/><attribute name="PDFLocation" value="D:\EPDM_Output\DW-EPL20.PDF"/><attribute name="ECO Details" value="Resin type change"/><attribute name="ECO Reason" value="New"/><attribute name="Code" value="1"/><attribute name="State" value="Released"/><attribute name="Reference Count" value="23100.0"/></configuration></document><document aliasset="" id="EK960" idattribute="Number" idcfgname="Default" pdmweid="1327"><configuration name="Default" quantity="7700"><attribute name="Number" value="EK960"/><attribute name="Part Family" value="Resins"/><attribute name="Part Type" value="R"/><attribute name="Buy / Sell Unit" value="kg"/><attribute name="Revision" value="B01"/><attribute name="Conversion Ratio" value="1000"/><attribute name="Assigned To" value="AlisonS"/><attribute name="Description" value="Hardener Momentive EK960"/><attribute name="Factory Unit" value="gm"/><attribute name="PDFLocation" value="D:\EPDM_Output\DW-EK960.PDF"/><attribute name="ECO Details" value="Hardener type change"/><attribute name="ECO Reason" value="New"/><attribute name="Code" value="1"/><attribute name="State" value="Released"/><attribute name="Reference Count" value="7700.0"/></configuration></document></references></configuration></document></references></configuration></document><document aliasset="" id="GB1-5715-00-12" idattribute="Number" idcfgname="Default" pdmweid="4034"><configuration name="Default" quantity="1"><attribute name="Number" value="GB1-5715-00-12"/><attribute name="Part Family" value="0"/><attribute name="Part Type" value="P"/><attribute name="Buy / Sell Unit" value="ea"/><attribute name="Revision" value="A02"/><attribute name="Conversion Ratio" value="1"/><attribute name="Assigned To" value="TomA"/><attribute name="Description" value="Main Spar LH Front R Insert"/><attribute name="Factory Unit" value="ea"/><attribute name="PDFLocation" value="D:\EPDM_Output\DW-GB1-5715-00-12.PDF"/><attribute name="ECO Details" value="Main Spar LH Front R Insert"/><attribute name="ECO Reason" value="New"/><attribute name="Code" value="1"/><attribute name="State" value="Released"/><attribute name="Reference Count" value="1.0"/><references><document aliasset="" id="GB1-5110-03-00" idattribute="Number" idcfgname="Default" pdmweid="3043"><configuration name="Default" quantity="1"><attribute name="Number" value="GB1-5110-03-00"/><attribute name="Part Family" value="0"/><attribute name="Part Type" value="P"/><attribute name="Buy / Sell Unit" value="sqm"/><attribute name="Revision" value="A02"/><attribute name="Conversion Ratio" value="1"/><attribute name="Assigned To" value=""/><attribute name="Description" value="C200 Quasi-Isotropic Plate-8mm"/><attribute name="Factory Unit" value="sqm"/><attribute name="PDFLocation" value="D:\EPDM_Output\DW-GB1-5110-03-00.PDF"/><attribute name="ECO Details" value="C200 Quasi-Isotropic Plate-8mm"/><attribute name="ECO Reason" value="New"/><attribute name="Code" value="1"/><attribute name="State" value="Released"/><attribute name="Reference Count" value="1.0"/><references><document aliasset="" id="C200" idattribute="Number" idcfgname="Default" pdmweid="1016"><configuration name="Default" quantity="40"><attribute name="Number" value="C200"/><attribute name="Part Family" value="Fabrics"/><attribute name="Part Type" value="R"/><attribute name="Buy / Sell Unit" value="m"/><attribute name="Revision" value="A03"/><attribute name="Conversion Ratio" value="1"/><attribute name="Assigned To" value="TomA"/><attribute name="Description" value="EC Cramer CCC452"/><attribute name="Factory Unit" value="m"/><attribute name="PDFLocation" value="D:\EPDM_Output\DW-C200.PDF"/><attribute name="ECO Details" value="EC Cramer CCC452"/><attribute name="ECO Reason" value="New"/><attribute name="Code" value="1"/><attribute name="State" value="Released"/><attribute name="Reference Count" value="40.0"/></configuration></document><document aliasset="" id="EPL20" idattribute="Number" idcfgname="Default" pdmweid="1326"><configuration name="Default" quantity="6000"><attribute name="Number" value="EPL20"/><attribute name="Part Family" value="Resins"/><attribute name="Part Type" value="R"/><attribute name="Buy / Sell Unit" value="kg"/><attribute name="Revision" value="B01"/><attribute name="Conversion Ratio" value="1000"/><attribute name="Assigned To" value="AlisonS"/><attribute name="Description" value="Resin Momentive EPL20"/><attribute name="Factory Unit" value="gm"/><attribute name="PDFLocation" value="D:\EPDM_Output\DW-EPL20.PDF"/><attribute name="ECO Details" value="Resin type change"/><attribute name="ECO Reason" value="New"/><attribute name="Code" value="1"/><attribute name="State" value="Released"/><attribute name="Reference Count" value="6000.0"/></configuration></document><document aliasset="" id="EK960" idattribute="Number" idcfgname="Default" pdmweid="1327"><configuration name="Default" quantity="2000"><attribute name="Number" value="EK960"/><attribute name="Part Family" value="Resins"/><attribute name="Part Type" value="R"/><attribute name="Buy / Sell Unit" value="kg"/><attribute name="Revision" value="B01"/><attribute name="Conversion Ratio" value="1000"/><attribute name="Assigned To" value="AlisonS"/><attribute name="Description" value="Hardener Momentive EK960"/><attribute name="Factory Unit" value="gm"/><attribute name="PDFLocation" value="D:\EPDM_Output\DW-EK960.PDF"/><attribute name="ECO Details" value="Hardener type change"/><attribute name="ECO Reason" value="New"/><attribute name="Code" value="1"/><attribute name="State" value="Released"/><attribute name="Reference Count" value="2000.0"/></configuration></document></references></configuration></document></references></configuration></document><document aliasset="" id="GB1-5715-00-11" idattribute="Number" idcfgname="Default" pdmweid="4035"><configuration name="Default" quantity="1"><attribute name="Number" value="GB1-5715-00-11"/><attribute name="Part Family" value="0"/><attribute name="Part Type" value="P"/><attribute name="Buy / Sell Unit" value="ea"/><attribute name="Revision" value="A02"/><attribute name="Conversion Ratio" value="1"/><attribute name="Assigned To" value="TomA"/><attribute name="Description" value="Main Spar LH Front L Insert"/><attribute name="Factory Unit" value="ea"/><attribute name="PDFLocation" value="D:\EPDM_Output\DW-GB1-5715-00-11.PDF"/><attribute name="ECO Details" value="Main Spar LH Front L Insert"/><attribute name="ECO Reason" value="New"/><attribute name="Code" value="1"/><attribute name="State" value="Released"/><attribute name="Reference Count" value="1.0"/><references><document aliasset="" id="GB1-5110-03-00" idattribute="Number" idcfgname="Default" pdmweid="3043"><configuration name="Default" quantity="1"><attribute name="Number" value="GB1-5110-03-00"/><attribute name="Part Family" value="0"/><attribute name="Part Type" value="P"/><attribute name="Buy / Sell Unit" value="sqm"/><attribute name="Revision" value="A02"/><attribute name="Conversion Ratio" value="1"/><attribute name="Assigned To" value=""/><attribute name="Description" value="C200 Quasi-Isotropic Plate-8mm"/><attribute name="Factory Unit" value="sqm"/><attribute name="PDFLocation" value="D:\EPDM_Output\DW-GB1-5110-03-00.PDF"/><attribute name="ECO Details" value="C200 Quasi-Isotropic Plate-8mm"/><attribute name="ECO Reason" value="New"/><attribute name="Code" value="1"/><attribute name="State" value="Released"/><attribute name="Reference Count" value="1.0"/><references><document aliasset="" id="C200" idattribute="Number" idcfgname="Default" pdmweid="1016"><configuration name="Default" quantity="40"><attribute name="Number" value="C200"/><attribute name="Part Family" value="Fabrics"/><attribute name="Part Type" value="R"/><attribute name="Buy / Sell Unit" value="m"/><attribute name="Revision" value="A03"/><attribute name="Conversion Ratio" value="1"/><attribute name="Assigned To" value="TomA"/><attribute name="Description" value="EC Cramer CCC452"/><attribute name="Factory Unit" value="m"/><attribute name="PDFLocation" value="D:\EPDM_Output\DW-C200.PDF"/><attribute name="ECO Details" value="EC Cramer CCC452"/><attribute name="ECO Reason" value="New"/><attribute name="Code" value="1"/><attribute name="State" value="Released"/><attribute name="Reference Count" value="40.0"/></configuration></document><document aliasset="" id="EPL20" idattribute="Number" idcfgname="Default" pdmweid="1326"><configuration name="Default" quantity="6000"><attribute name="Number" value="EPL20"/><attribute name="Part Family" value="Resins"/><attribute name="Part Type" value="R"/><attribute name="Buy / Sell Unit" value="kg"/><attribute name="Revision" value="B01"/><attribute name="Conversion Ratio" value="1000"/><attribute name="Assigned To" value="AlisonS"/><attribute name="Description" value="Resin Momentive EPL20"/><attribute name="Factory Unit" value="gm"/><attribute name="PDFLocation" value="D:\EPDM_Output\DW-EPL20.PDF"/><attribute name="ECO Details" value="Resin type change"/><attribute name="ECO Reason" value="New"/><attribute name="Code" value="1"/><attribute name="State" value="Released"/><attribute name="Reference Count" value="6000.0"/></configuration></document><document aliasset="" id="EK960" idattribute="Number" idcfgname="Default" pdmweid="1327"><configuration name="Default" quantity="2000"><attribute name="Number" value="EK960"/><attribute name="Part Family" value="Resins"/><attribute name="Part Type" value="R"/><attribute name="Buy / Sell Unit" value="kg"/><attribute name="Revision" value="B01"/><attribute name="Conversion Ratio" value="1000"/><attribute name="Assigned To" value="AlisonS"/><attribute name="Description" value="Hardener Momentive EK960"/><attribute name="Factory Unit" value="gm"/><attribute name="PDFLocation" value="D:\EPDM_Output\DW-EK960.PDF"/><attribute name="ECO Details" value="Hardener type change"/><attribute name="ECO Reason" value="New"/><attribute name="Code" value="1"/><attribute name="State" value="Released"/><attribute name="Reference Count" value="2000.0"/></configuration></document></references></configuration></document></references></configuration></document><document aliasset="" id="GB1-5715-00-13" idattribute="Number" idcfgname="Default" pdmweid="4036"><configuration name="Default" quantity="1"><attribute name="Number" value="GB1-5715-00-13"/><attribute name="Part Family" value="0"/><attribute name="Part Type" value="P"/><attribute name="Buy / Sell Unit" value="ea"/><attribute name="Revision" value="A02"/><attribute name="Conversion Ratio" value="1"/><attribute name="Assigned To" value="TomA"/><attribute name="Description" value="Main Spar LH Rear L Insert"/><attribute name="Factory Unit" value="ea"/><attribute name="PDFLocation" value="D:\EPDM_Output\DW-GB1-5715-00-13.PDF"/><attribute name="ECO Details" value="Main Spar LH Rear L Insert"/><attribute name="ECO Reason" value="New"/><attribute name="Code" value="1"/><attribute name="State" value="Released"/><attribute name="Reference Count" value="1.0"/><references><document aliasset="" id="GB1-5110-03-00" idattribute="Number" idcfgname="Default" pdmweid="3043"><configuration name="Default" quantity="1"><attribute name="Number" value="GB1-5110-03-00"/><attribute name="Part Family" value="0"/><attribute name="Part Type" value="P"/><attribute name="Buy / Sell Unit" value="sqm"/><attribute name="Revision" value="A02"/><attribute name="Conversion Ratio" value="1"/><attribute name="Assigned To" value=""/><attribute name="Description" value="C200 Quasi-Isotropic Plate-8mm"/><attribute name="Factory Unit" value="sqm"/><attribute name="PDFLocation" value="D:\EPDM_Output\DW-GB1-5110-03-00.PDF"/><attribute name="ECO Details" value="C200 Quasi-Isotropic Plate-8mm"/><attribute name="ECO Reason" value="New"/><attribute name="Code" value="1"/><attribute name="State" value="Released"/><attribute name="Reference Count" value="1.0"/><references><document aliasset="" id="C200" idattribute="Number" idcfgname="Default" pdmweid="1016"><configuration name="Default" quantity="40"><attribute name="Number" value="C200"/><attribute name="Part Family" value="Fabrics"/><attribute name="Part Type" value="R"/><attribute name="Buy / Sell Unit" value="m"/><attribute name="Revision" value="A03"/><attribute name="Conversion Ratio" value="1"/><attribute name="Assigned To" value="TomA"/><attribute name="Description" value="EC Cramer CCC452"/><attribute name="Factory Unit" value="m"/><attribute name="PDFLocation" value="D:\EPDM_Output\DW-C200.PDF"/><attribute name="ECO Details" value="EC Cramer CCC452"/><attribute name="ECO Reason" value="New"/><attribute name="Code" value="1"/><attribute name="State" value="Released"/><attribute name="Reference Count" value="40.0"/></configuration></document><document aliasset="" id="EPL20" idattribute="Number" idcfgname="Default" pdmweid="1326"><configuration name="Default" quantity="6000"><attribute name="Number" value="EPL20"/><attribute name="Part Family" value="Resins"/><attribute name="Part Type" value="R"/><attribute name="Buy / Sell Unit" value="kg"/><attribute name="Revision" value="B01"/><attribute name="Conversion Ratio" value="1000"/><attribute name="Assigned To" value="AlisonS"/><attribute name="Description" value="Resin Momentive EPL20"/><attribute name="Factory Unit" value="gm"/><attribute name="PDFLocation" value="D:\EPDM_Output\DW-EPL20.PDF"/><attribute name="ECO Details" value="Resin type change"/><attribute name="ECO Reason" value="New"/><attribute name="Code" value="1"/><attribute name="State" value="Released"/><attribute name="Reference Count" value="6000.0"/></configuration></document><document aliasset="" id="EK960" idattribute="Number" idcfgname="Default" pdmweid="1327"><configuration name="Default" quantity="2000"><attribute name="Number" value="EK960"/><attribute name="Part Family" value="Resins"/><attribute name="Part Type" value="R"/><attribute name="Buy / Sell Unit" value="kg"/><attribute name="Revision" value="B01"/><attribute name="Conversion Ratio" value="1000"/><attribute name="Assigned To" value="AlisonS"/><attribute name="Description" value="Hardener Momentive EK960"/><attribute name="Factory Unit" value="gm"/><attribute name="PDFLocation" value="D:\EPDM_Output\DW-EK960.PDF"/><attribute name="ECO Details" value="Hardener type change"/><attribute name="ECO Reason" value="New"/><attribute name="Code" value="1"/><attribute name="State" value="Released"/><attribute name="Reference Count" value="2000.0"/></configuration></document></references></configuration></document></references></configuration></document><document aliasset="" id="GB1-5715-00-14" idattribute="Number" idcfgname="Default" pdmweid="4037"><configuration name="Default" quantity="1"><attribute name="Number" value="GB1-5715-00-14"/><attribute name="Part Family" value="0"/><attribute name="Part Type" value="P"/><attribute name="Buy / Sell Unit" value="ea"/><attribute name="Revision" value="A02"/><attribute name="Conversion Ratio" value="1"/><attribute name="Assigned To" value="TomA"/><attribute name="Description" value="Main Spar LH Rear R Insert"/><attribute name="Factory Unit" value="ea"/><attribute name="PDFLocation" value="D:\EPDM_Output\DW-GB1-5715-00-14.PDF"/><attribute name="ECO Details" value="Main Spar LH Rear R Insert"/><attribute name="ECO Reason" value="New"/><attribute name="Code" value="1"/><attribute name="State" value="Released"/><attribute name="Reference Count" value="1.0"/><references><document aliasset="" id="GB1-5110-03-00" idattribute="Number" idcfgname="Default" pdmweid="3043"><configuration name="Default" quantity="1"><attribute name="Number" value="GB1-5110-03-00"/><attribute name="Part Family" value="0"/><attribute name="Part Type" value="P"/><attribute name="Buy / Sell Unit" value="sqm"/><attribute name="Revision" value="A02"/><attribute name="Conversion Ratio" value="1"/><attribute name="Assigned To" value=""/><attribute name="Description" value="C200 Quasi-Isotropic Plate-8mm"/><attribute name="Factory Unit" value="sqm"/><attribute name="PDFLocation" value="D:\EPDM_Output\DW-GB1-5110-03-00.PDF"/><attribute name="ECO Details" value="C200 Quasi-Isotropic Plate-8mm"/><attribute name="ECO Reason" value="New"/><attribute name="Code" value="1"/><attribute name="State" value="Released"/><attribute name="Reference Count" value="1.0"/><references><document aliasset="" id="C200" idattribute="Number" idcfgname="Default" pdmweid="1016"><configuration name="Default" quantity="40"><attribute name="Number" value="C200"/><attribute name="Part Family" value="Fabrics"/><attribute name="Part Type" value="R"/><attribute name="Buy / Sell Unit" value="m"/><attribute name="Revision" value="A03"/><attribute name="Conversion Ratio" value="1"/><attribute name="Assigned To" value="TomA"/><attribute name="Description" value="EC Cramer CCC452"/><attribute name="Factory Unit" value="m"/><attribute name="PDFLocation" value="D:\EPDM_Output\DW-C200.PDF"/><attribute name="ECO Details" value="EC Cramer CCC452"/><attribute name="ECO Reason" value="New"/><attribute name="Code" value="1"/><attribute name="State" value="Released"/><attribute name="Reference Count" value="40.0"/></configuration></document><document aliasset="" id="EPL20" idattribute="Number" idcfgname="Default" pdmweid="1326"><configuration name="Default" quantity="6000"><attribute name="Number" value="EPL20"/><attribute name="Part Family" value="Resins"/><attribute name="Part Type" value="R"/><attribute name="Buy / Sell Unit" value="kg"/><attribute name="Revision" value="B01"/><attribute name="Conversion Ratio" value="1000"/><attribute name="Assigned To" value="AlisonS"/><attribute name="Description" value="Resin Momentive EPL20"/><attribute name="Factory Unit" value="gm"/><attribute name="PDFLocation" value="D:\EPDM_Output\DW-EPL20.PDF"/><attribute name="ECO Details" value="Resin type change"/><attribute name="ECO Reason" value="New"/><attribute name="Code" value="1"/><attribute name="State" value="Released"/><attribute name="Reference Count" value="6000.0"/></configuration></document><document aliasset="" id="EK960" idattribute="Number" idcfgname="Default" pdmweid="1327"><configuration name="Default" quantity="2000"><attribute name="Number" value="EK960"/><attribute name="Part Family" value="Resins"/><attribute name="Part Type" value="R"/><attribute name="Buy / Sell Unit" value="kg"/><attribute name="Revision" value="B01"/><attribute name="Conversion Ratio" value="1000"/><attribute name="Assigned To" value="AlisonS"/><attribute name="Description" value="Hardener Momentive EK960"/><attribute name="Factory Unit" value="gm"/><attribute name="PDFLocation" value="D:\EPDM_Output\DW-EK960.PDF"/><attribute name="ECO Details" value="Hardener type change"/><attribute name="ECO Reason" value="New"/><attribute name="Code" value="1"/><attribute name="State" value="Released"/><attribute name="Reference Count" value="2000.0"/></configuration></document></references></configuration></document></references></configuration></document><document aliasset="" id="GB1-5715-00-21" idattribute="Number" idcfgname="Default" pdmweid="4038"><configuration name="Default" quantity="1"><attribute name="Number" value="GB1-5715-00-21"/><attribute name="Part Family" value="0"/><attribute name="Part Type" value="P"/><attribute name="Buy / Sell Unit" value="ea"/><attribute name="Revision" value="A02"/><attribute name="Conversion Ratio" value="1"/><attribute name="Assigned To" value="TomA"/><attribute name="Description" value="Main Spar LH Front Center Core"/><attribute name="Factory Unit" value="ea"/><attribute name="PDFLocation" value="D:\EPDM_Output\DW-GB1-5715-00-21.PDF"/><attribute name="ECO Details" value="Main Spar LH Front Center Core"/><attribute name="ECO Reason" value="New"/><attribute name="Code" value="1"/><attribute name="State" value="Released"/><attribute name="Reference Count" value="1.0"/><references><document aliasset="" id="R51IG-F_8mm" idattribute="Number" idcfgname="Default" pdmweid="2970"><configuration name="Default" quantity="1"><attribute name="Number" value="R51IG-F_8mm"/><attribute name="Part Family" value="Core"/><attribute name="Part Type" value="R"/><attribute name="Buy / Sell Unit" value="ea"/><attribute name="Revision" value="A01"/><attribute name="Conversion Ratio" value="3"/><attribute name="Assigned To" value="AlisonS"/><attribute name="Description" value="Rohacell R51IG-F 8x1300x2600"/><attribute name="Factory Unit" value="sqm"/><attribute name="PDFLocation" value="D:\EPDM_Output\DW-R51IG-F_8mm.PDF"/><attribute name="ECO Details" value="Rohacell R51IG-F 8x1300x2600"/><attribute name="ECO Reason" value="New"/><attribute name="Code" value="1"/><attribute name="State" value="Released"/><attribute name="Reference Count" value="1.0"/></configuration></document></references></configuration></document><document aliasset="" id="GB1-5715-00-22" idattribute="Number" idcfgname="Default" pdmweid="4039"><configuration name="Default" quantity="1"><attribute name="Number" value="GB1-5715-00-22"/><attribute name="Part Family" value="0"/><attribute name="Part Type" value="P"/><attribute name="Buy / Sell Unit" value="ea"/><attribute name="Revision" value="A02"/><attribute name="Conversion Ratio" value="1"/><attribute name="Assigned To" value=""/><attribute name="Description" value="Main Spar LH Front Tapering Core"/><attribute name="Factory Unit" value="ea"/><attribute name="PDFLocation" value="D:\EPDM_Output\DW-GB1-5715-00-22.PDF"/><attribute name="ECO Details" value="Main Spar LH Front Tapering Core"/><attribute name="ECO Reason" value="New"/><attribute name="Code" value="1"/><attribute name="State" value="Released"/><attribute name="Reference Count" value="1.0"/><references><document aliasset="" id="R51IG-F_8mm" idattribute="Number" idcfgname="Default" pdmweid="2970"><configuration name="Default" quantity="1"><attribute name="Number" value="R51IG-F_8mm"/><attribute name="Part Family" value="Core"/><attribute name="Part Type" value="R"/><attribute name="Buy / Sell Unit" value="ea"/><attribute name="Revision" value="A01"/><attribute name="Conversion Ratio" value="3"/><attribute name="Assigned To" value="AlisonS"/><attribute name="Description" value="Rohacell R51IG-F 8x1300x2600"/><attribute name="Factory Unit" value="sqm"/><attribute name="PDFLocation" value="D:\EPDM_Output\DW-R51IG-F_8mm.PDF"/><attribute name="ECO Details" value="Rohacell R51IG-F 8x1300x2600"/><attribute name="ECO Reason" value="New"/><attribute name="Code" value="1"/><attribute name="State" value="Released"/><attribute name="Reference Count" value="1.0"/></configuration></document></references></configuration></document><document aliasset="" id="GB1-5715-00-23" idattribute="Number" idcfgname="Default" pdmweid="4040"><configuration name="Default" quantity="1"><attribute name="Number" value="GB1-5715-00-23"/><attribute name="Part Family" value="0"/><attribute name="Part Type" value="P"/><attribute name="Buy / Sell Unit" value="ea"/><attribute name="Revision" value="A02"/><attribute name="Conversion Ratio" value="1"/><attribute name="Assigned To" value=""/><attribute name="Description" value="Main Spar LH Rear Center Core"/><attribute name="Factory Unit" value="ea"/><attribute name="PDFLocation" value="D:\EPDM_Output\DW-GB1-5715-00-23.PDF"/><attribute name="ECO Details" value="Main Spar LH Rear Center Core"/><attribute name="ECO Reason" value="New"/><attribute name="Code" value="1"/><attribute name="State" value="Released"/><attribute name="Reference Count" value="1.0"/><references><document aliasset="" id="R51IG-F_8mm" idattribute="Number" idcfgname="Default" pdmweid="2970"><configuration name="Default" quantity="1"><attribute name="Number" value="R51IG-F_8mm"/><attribute name="Part Family" value="Core"/><attribute name="Part Type" value="R"/><attribute name="Buy / Sell Unit" value="ea"/><attribute name="Revision" value="A01"/><attribute name="Conversion Ratio" value="3"/><attribute name="Assigned To" value="AlisonS"/><attribute name="Description" value="Rohacell R51IG-F 8x1300x2600"/><attribute name="Factory Unit" value="sqm"/><attribute name="PDFLocation" value="D:\EPDM_Output\DW-R51IG-F_8mm.PDF"/><attribute name="ECO Details" value="Rohacell R51IG-F 8x1300x2600"/><attribute name="ECO Reason" value="New"/><attribute name="Code" value="1"/><attribute name="State" value="Released"/><attribute name="Reference Count" value="1.0"/></configuration></document></references></configuration></document><document aliasset="" id="GB1-5715-00-24" idattribute="Number" idcfgname="Default" pdmweid="4041"><configuration name="Default" quantity="1"><attribute name="Number" value="GB1-5715-00-24"/><attribute name="Part Family" value="0"/><attribute name="Part Type" value="P"/><attribute name="Buy / Sell Unit" value="ea"/><attribute name="Revision" value="A02"/><attribute name="Conversion Ratio" value="1"/><attribute name="Assigned To" value=""/><attribute name="Description" value="Main Spar LH Rear Tapering Core"/><attribute name="Factory Unit" value="ea"/><attribute name="PDFLocation" value="D:\EPDM_Output\DW-GB1-5715-00-24.PDF"/><attribute name="ECO Details" value="Main Spar LH Rear Tapering Core"/><attribute name="ECO Reason" value="New"/><attribute name="Code" value="1"/><attribute name="State" value="Released"/><attribute name="Reference Count" value="1.0"/><references><document aliasset="" id="R51IG-F_8mm" idattribute="Number" idcfgname="Default" pdmweid="2970"><configuration name="Default" quantity="1"><attribute name="Number" value="R51IG-F_8mm"/><attribute name="Part Family" value="Core"/><attribute name="Part Type" value="R"/><attribute name="Buy / Sell Unit" value="ea"/><attribute name="Revision" value="A01"/><attribute name="Conversion Ratio" value="3"/><attribute name="Assigned To" value="AlisonS"/><attribute name="Description" value="Rohacell R51IG-F 8x1300x2600"/><attribute name="Factory Unit" value="sqm"/><attribute name="PDFLocation" value="D:\EPDM_Output\DW-R51IG-F_8mm.PDF"/><attribute name="ECO Details" value="Rohacell R51IG-F 8x1300x2600"/><attribute name="ECO Reason" value="New"/><attribute name="Code" value="1"/><attribute name="State" value="Released"/><attribute name="Reference Count" value="1.0"/></configuration></document></references></configuration></document><document aliasset="" id="GB1-5715-00-25" idattribute="Number" idcfgname="Default" pdmweid="4042"><configuration name="Default" quantity="1"><attribute name="Number" value="GB1-5715-00-25"/><attribute name="Part Family" value="0"/><attribute name="Part Type" value="P"/><attribute name="Buy / Sell Unit" value="ea"/><attribute name="Revision" value="A02"/><attribute name="Conversion Ratio" value="1"/><attribute name="Assigned To" value=""/><attribute name="Description" value="Main Spar LH Web Core"/><attribute name="Factory Unit" value="ea"/><attribute name="PDFLocation" value="D:\EPDM_Output\DW-GB1-5715-00-25.PDF"/><attribute name="ECO Details" value="Main Spar LH Web Core"/><attribute name="ECO Reason" value="New"/><attribute name="Code" value="1"/><attribute name="State" value="Released"/><attribute name="Reference Count" value="1.0"/><references><document aliasset="" id="R51IG-F_8mm" idattribute="Number" idcfgname="Default" pdmweid="2970"><configuration name="Default" quantity="1"><attribute name="Number" value="R51IG-F_8mm"/><attribute name="Part Family" value="Core"/><attribute name="Part Type" value="R"/><attribute name="Buy / Sell Unit" value="ea"/><attribute name="Revision" value="A01"/><attribute name="Conversion Ratio" value="3"/><attribute name="Assigned To" value="AlisonS"/><attribute name="Description" value="Rohacell R51IG-F 8x1300x2600"/><attribute name="Factory Unit" value="sqm"/><attribute name="PDFLocation" value="D:\EPDM_Output\DW-R51IG-F_8mm.PDF"/><attribute name="ECO Details" value="Rohacell R51IG-F 8x1300x2600"/><attribute name="ECO Reason" value="New"/><attribute name="Code" value="1"/><attribute name="State" value="Released"/><attribute name="Reference Count" value="1.0"/></configuration></document></references></configuration></document><document aliasset="" id="GB1-5715-00-91" idattribute="Number" idcfgname="Default" pdmweid="8059"><configuration name="Default" quantity="1"><attribute name="Number" value="GB1-5715-00-91"/><attribute name="Part Family" value="0"/><attribute name="Part Type" value="R"/><attribute name="Buy / Sell Unit" value="ea"/><attribute name="Revision" value="B01"/><attribute name="Conversion Ratio" value="1"/><attribute name="Assigned To" value="AlisonS"/><attribute name="Description" value="Aquapour Core LH"/><attribute name="Factory Unit" value="ea"/><attribute name="PDFLocation" value="D:\EPDM_Output\DW-GB1-5715-00-91.PDF"/><attribute name="ECO Details" value="Aquapour Core LH"/><attribute name="ECO Reason" value="New"/><attribute name="Code" value="1"/><attribute name="State" value="Released"/><attribute name="Reference Count" value="1.0"/></configuration></document></references></configuration></document></transaction></transactions></xml>
