<xml><transactions><transaction date="1502455346" type="wf_export_document_attributes" vaultname="Testbox"><document aliasset="" id="GB1-7611-11-00" idattribute="Number" idcfgname="Default" pdmweid="3245"><configuration name="Default" quantity="1"><attribute name="Number" value="GB1-7611-11-00"/><attribute name="Part Family" value="0"/><attribute name="Part Type" value="R"/><attribute name="Buy / Sell Unit" value="ea"/><attribute name="Revision" value="A01"/><attribute name="Conversion Ratio" value="1"/><attribute name="Assigned To" value="TomA"/><attribute name="Description" value="Assy, Frame, Throttle Control"/><attribute name="Factory Unit" value="ea"/><attribute name="PDFLocation" value="D:\EPDM_Output\DW-GB1-7611-11-00.PDF"/><attribute name="ECO Details" value="Throttle quadrant frame, 1st"/><attribute name="ECO Reason" value="New"/><attribute name="Code" value="1"/><attribute name="State" value="Released"/><attribute name="Reference Count" value="1.0"/><references><document aliasset="" id="GB1-7611-11-01" idattribute="Number" idcfgname="Default" pdmweid="3241"><configuration name="Default" quantity="1"><attribute name="Number" value="GB1-7611-11-01"/><attribute name="Part Family" value="0"/><attribute name="Part Type" value="R"/><attribute name="Buy / Sell Unit" value="ea"/><attribute name="Revision" value="A01"/><attribute name="Conversion Ratio" value="1"/><attribute name="Assigned To" value="AlisonS"/><attribute name="Description" value="Plate 1, Throttle Control Frame"/><attribute name="Factory Unit" value="ea"/><attribute name="PDFLocation" value="D:\EPDM_Output\DW-GB1-7611-11-01.PDF"/><attribute name="ECO Details" value="Plate, first release"/><attribute name="ECO Reason" value="New"/><attribute name="Code" value="1"/><attribute name="State" value="Released"/><attribute name="Reference Count" value="1.0"/></configuration></document><document aliasset="" id="GB1-7611-11-02" idattribute="Number" idcfgname="Default" pdmweid="3242"><configuration name="Default" quantity="1"><attribute name="Number" value="GB1-7611-11-02"/><attribute name="Part Family" value="0"/><attribute name="Part Type" value="R"/><attribute name="Buy / Sell Unit" value="ea"/><attribute name="Revision" value="A01"/><attribute name="Conversion Ratio" value="1"/><attribute name="Assigned To" value="TomA"/><attribute name="Description" value="Plate 2, Throttle Control Frame"/><attribute name="Factory Unit" value="ea"/><attribute name="PDFLocation" value="D:\EPDM_Output\DW-GB1-7611-11-02.PDF"/><attribute name="ECO Details" value="Plate, first release"/><attribute name="ECO Reason" value="New"/><attribute name="Code" value="1"/><attribute name="State" value="Released"/><attribute name="Reference Count" value="1.0"/></configuration></document><document aliasset="" id="GB1-7611-11-03" idattribute="Number" idcfgname="Default" pdmweid="3243"><configuration name="Default" quantity="1"><attribute name="Number" value="GB1-7611-11-03"/><attribute name="Part Family" value="0"/><attribute name="Part Type" value="R"/><attribute name="Buy / Sell Unit" value="ea"/><attribute name="Revision" value="A01"/><attribute name="Conversion Ratio" value="1"/><attribute name="Assigned To" value="TomA"/><attribute name="Description" value="Plate 3, Throttle Control Frame"/><attribute name="Factory Unit" value="ea"/><attribute name="PDFLocation" value="D:\EPDM_Output\DW-GB1-7611-11-03.PDF"/><attribute name="ECO Details" value="Plate, first release"/><attribute name="ECO Reason" value="New"/><attribute name="Code" value="1"/><attribute name="State" value="Released"/><attribute name="Reference Count" value="1.0"/></configuration></document><document aliasset="" id="GB1-7611-11-04" idattribute="Number" idcfgname="Default" pdmweid="3244"><configuration name="Default" quantity="1"><attribute name="Number" value="GB1-7611-11-04"/><attribute name="Part Family" value="0"/><attribute name="Part Type" value="R"/><attribute name="Buy / Sell Unit" value="ea"/><attribute name="Revision" value="A01"/><attribute name="Conversion Ratio" value="1"/><attribute name="Assigned To" value=""/><attribute name="Description" value="Plate 4, Throttle Control Frame"/><attribute name="Factory Unit" value="ea"/><attribute name="PDFLocation" value="D:\EPDM_Output\DW-GB1-7611-11-04.PDF"/><attribute name="ECO Details" value="Plate, first release"/><attribute name="ECO Reason" value="New"/><attribute name="Code" value="1"/><attribute name="State" value="Released"/><attribute name="Reference Count" value="1.0"/></configuration></document></references></configuration></document></transaction></transactions></xml>
