<xml><transactions><transaction date="1436546756" type="wf_export_document_attributes" vaultname="Testbox"><document aliasset="" id="GB1_Paint" idattribute="Number" idcfgname="Default" pdmweid="12948"><configuration name="Default" quantity="1"><attribute name="Number" value="GB1_Paint"/><attribute name="Part Family" value="0"/><attribute name="Part Type" value="P"/><attribute name="Buy / Sell Unit" value="ea"/><attribute name="Revision" value="A01P"/><attribute name="Conversion Ratio" value="1"/><attribute name="Assigned To" value="AlisonS"/><attribute name="Description" value="GB1 Paint Assembly"/><attribute name="Factory Unit" value="ea"/><attribute name="PDFLocation" value="D:\EPDM_Output\DW-GB1 Post Cure.PDF"/><attribute name="ECO Details" value="GB1 Paint Assembly"/><attribute name="ECO Reason" value="New"/><attribute name="Code" value="1"/><attribute name="State" value="Released"/><attribute name="Reference Count" value="1.0"/><references><document aliasset="" id="GB1_Post-Cure" idattribute="Number" idcfgname="Default" pdmweid="12137"><configuration name="Default" quantity="1"><attribute name="Number" value="GB1_Post-Cure"/><attribute name="Part Family" value="0"/><attribute name="Part Type" value="P"/><attribute name="Buy / Sell Unit" value="ea"/><attribute name="Revision" value="A01P"/><attribute name="Conversion Ratio" value="1"/><attribute name="Assigned To" value="AlisonS"/><attribute name="Description" value="GB1 Post Cure Assembly"/><attribute name="Factory Unit" value="ea"/><attribute name="PDFLocation" value="D:\EPDM_Output\DW-GB1 Test Assy.PDF"/><attribute name="ECO Details" value="GB1 Post Cure Assembly"/><attribute name="ECO Reason" value="New"/><attribute name="Code" value="1"/><attribute name="State" value="Released"/><attribute name="Reference Count" value="1.0"/></configuration></document></references></configuration></document></transaction></transactions></xml>
