<xml><transactions><transaction date="1618436000" type="wf_export_document_attributes" vaultname="Testbox"><document aliasset="" id="96880A530_MIL SPEC PAN HEAD PHILLIPS MACHINE SCREW" idattribute="Number" idcfgname="Default" pdmweid="31905"><configuration name="Default" quantity="1"><attribute name="Number" value="96880A530_MIL SPEC PAN HEAD PHILLIPS MACHINE SCREW"/><attribute name="Part Family" value="0"/><attribute name="Part Type" value="R"/><attribute name="Buy / Sell Unit" value="ea"/><attribute name="Revision" value="A02"/><attribute name="Conversion Ratio" value="1"/><attribute name="Assigned To" value="AlisonS"/><attribute name="Description" value="Screw, Pan Hd, #10-32UNF x 0.875"/><attribute name="Factory Unit" value="ea"/><attribute name="PDFLocation" value="D:\EPDM_Output\DW-96880A530_MIL SPEC PAN HEAD PHILLIPS MACHINE SCREW.PDF"/><attribute name="ECO Details" value="Screw, Pan Hd, #10-32UNF x 0.875"/><attribute name="ECO Reason" value="New"/><attribute name="Code" value=""/><attribute name="State" value="Released"/><attribute name="Reference Count" value="1.0"/></configuration></document></transaction></transactions></xml>
